AUTHORS
LICENSE
MANIFEST.in
README.md
barcodebattler-reader
setup.py
barcode_battler_engine.egg-info/PKG-INFO
barcode_battler_engine.egg-info/SOURCES.txt
barcode_battler_engine.egg-info/dependency_links.txt
barcode_battler_engine.egg-info/top_level.txt
barcodebattler/__init__.py
barcodebattler/bb2/__init__.py
barcodebattler/bb2/barcode_data.py
barcodebattler/bb2/builder.py
barcodebattler/bb2/constants.py
barcodebattler/bb2/tests/__init__.py
barcodebattler/bb2/tests/test_builder.py
requirements/base.pip
requirements/dev.pip