Metadata-Version: 2.1
Name: barcode-battler-engine
Version: 0.1.0
Summary: Set of tools to simulate Barcode Battler II functionality.
Home-page: https://github.com/VITIMan/barcode-battler-engine.git
Author: Victoriano Navarro, VITIMan
Author-email: bimbiribase@protonmail.com
License: GPL3
Classifier: Environment :: Plugins
Classifier: Intended Audience :: Developers
Classifier: Intended Audience :: End Users/Desktop
Classifier: License :: OSI Approved :: GNU General Public License v3 (GPLv3)
Classifier: Operating System :: OS Independent
Classifier: Programming Language :: Python :: 3
Classifier: Programming Language :: Python :: 3 :: Only
Classifier: Programming Language :: Python :: 3.9
Classifier: Topic :: Software Development :: Libraries :: Python Modules
Classifier: Topic :: Games/Entertainment :: Role-Playing
Requires-Python: >=3.9
License-File: LICENSE
License-File: AUTHORS
